<?xml version="1.0" encoding="utf-8" ?>
<odoo>
    <data>
        <record id="manager_tags_list_view" model="ir.ui.view">
            <field name="name">manager.tags.list.view</field>
            <field name="model">manager.tags</field>
            <field name="arch" type="xml">
                <tree>
                    <field name="manager_id"/>
                    <field name="active"/>
                </tree>
            </field>
        </record>

        <record id="manager_tags_form_view" model="ir.ui.view">
            <field name="name">manager.tags.form.view</field>
            <field name="model">manager.tags</field>
            <field name="arch" type="xml">
                <form>
                    <sheet>
                        <group>
                            <group>
                                <field name="manager_id"/>
                            </group>
                            <group>
                                <field name="active" widget="boolean_toggle"/>
                            </group>
                        </group>
                    </sheet>
                </form>
            </field>
        </record>
         <record id="supervisor_tags_action" model="ir.actions.act_window">
            <field name="name">Manager Tags</field>
            <field name="res_model">manager.tags</field>
            <field name="view_mode">tree,form</field>
        </record>
    </data>
</odoo>
